{"name":"Creación Rol Gestor","id":"gestionar-roles-para-acceso-de-los-colaboradores;creación-rol-gestor","testSteps":[{"number":1,"description":"Given que el Gestor Senior/Admin inicia la sesion con usuario jcaraballo@summa-sci.com con clave S4p+*2022++**","duration":253389,"startTime":"2023-03-03T12:50:23.702280900-05:00[America/Bogota]","screenshots":[{"screenshot":"fbb6356931cf9ad79f805506ff5f9cad1f8625658d09e413d3649544129bbcbc.png","timeStamp":1677866077092}],"result":"SUCCESS","precondition":false,"level":0,"children":[{"number":2,"description":"Gestor home page","duration":19203,"startTime":"2023-03-03T12:50:23.703266300-05:00[America/Bogota]","screenshots":[{"screenshot":"2a7791ba15962f8c5aaf5c7dda8ec8e08a9c8b927ab7a70adb90a7d966fe0fb6.png","timeStamp":1677865842906}],"result":"SUCCESS","precondition":false,"level":1,"children":[{"number":3,"description":"Gestor opens the https://app-expcolaborador-frontend-qa.azurewebsites.net","duration":19201,"startTime":"2023-03-03T12:50:23.704263600-05:00[America/Bogota]","screenshots":[{"screenshot":"2a7791ba15962f8c5aaf5c7dda8ec8e08a9c8b927ab7a70adb90a7d966fe0fb6.png","timeStamp":1677865842905}],"result":"SUCCESS","precondition":false,"level":2}]},{"number":4,"description":"Gestor login dir act","duration":234182,"startTime":"2023-03-03T12:50:42.908010700-05:00[America/Bogota]","screenshots":[{"screenshot":"fbb6356931cf9ad79f805506ff5f9cad1f8625658d09e413d3649544129bbcbc.png","timeStamp":1677866077090}],"result":"SUCCESS","precondition":false,"level":1,"children":[{"number":5,"description":"Gestor clicks on Caja USER","duration":6939,"startTime":"2023-03-03T12:50:42.917113400-05:00[America/Bogota]","screenshots":[{"screenshot":"9834fd6587d03dd41c2965c9276fb5f2c2ed3950183359ff83d253793bf32d04.png","timeStamp":1677865849857}],"result":"SUCCESS","precondition":false,"level":2},{"number":6,"description":"Gestor present","duration":3329,"startTime":"2023-03-03T12:50:49.858034600-05:00[America/Bogota]","screenshots":[{"screenshot":"2db3a90e05d8ae11b6caf3015d504b9d257b01f8f12128e43277123ff81cd896.png","timeStamp":1677865853187}],"result":"SUCCESS","precondition":false,"level":2},{"number":7,"description":"Gestor clicks on Caja USER","duration":343,"startTime":"2023-03-03T12:50:53.188065200-05:00[America/Bogota]","screenshots":[{"screenshot":"7b6c6fb56f5f5e55716bc7e04a0de3052c40e5c08876f3ec04aeaf0aaf6552e8.png","timeStamp":1677865853531}],"result":"SUCCESS","precondition":false,"level":2},{"number":8,"description":"Gestor enters \u0027jcaraballo@summa-sci.com\u0027 into Caja USER","duration":477,"startTime":"2023-03-03T12:50:53.532885-05:00[America/Bogota]","screenshots":[{"screenshot":"ec091b913a3ab7a97628b42ceebc5768fe578dfb2522bb5fae6794a6775c18cc.png","timeStamp":1677865854010}],"result":"SUCCESS","precondition":false,"level":2},{"number":9,"description":"Gestor clicks on BOTTN NEXT","duration":384,"startTime":"2023-03-03T12:50:54.011012100-05:00[America/Bogota]","screenshots":[{"screenshot":"63a8824d36e3acc6bf22550592f833c3c426151d154fbafa193b78c57bca4e23.png","timeStamp":1677865854395}],"result":"SUCCESS","precondition":false,"level":2},{"number":10,"description":"Gestor present","duration":9728,"startTime":"2023-03-03T12:50:54.396199900-05:00[America/Bogota]","screenshots":[{"screenshot":"d94aa94c527ee40ac618e88fb00ff55b728d2411c036eed21c1e96ce24d06f89.png","timeStamp":1677865864125}],"result":"SUCCESS","precondition":false,"level":2},{"number":11,"description":"Gestor clicks on Caja PASS","duration":219,"startTime":"2023-03-03T12:51:04.126090-05:00[America/Bogota]","screenshots":[{"screenshot":"d94aa94c527ee40ac618e88fb00ff55b728d2411c036eed21c1e96ce24d06f89.png","timeStamp":1677865864345}],"result":"SUCCESS","precondition":false,"level":2},{"number":12,"description":"Gestor enters \u0027S4p+*2022++**\u0027 into Caja PASS","duration":283,"startTime":"2023-03-03T12:51:04.345933400-05:00[America/Bogota]","screenshots":[{"screenshot":"0ec5215cf4b3791a1123b248b2e043749e8de93a99362f31afd0b1197e8c5d31.png","timeStamp":1677865864629}],"result":"SUCCESS","precondition":false,"level":2},{"number":13,"description":"Gestor clicks on BOTTON SIGN IN","duration":5576,"startTime":"2023-03-03T12:51:04.630917400-05:00[America/Bogota]","screenshots":[{"screenshot":"dcb4ade70be63bb68dbfed79926b7f02f844f9252ca11fb80a8e13df4572f749.png","timeStamp":1677865870207}],"result":"SUCCESS","precondition":false,"level":2},{"number":14,"description":"Gestor wait","duration":5255,"startTime":"2023-03-03T12:51:10.208193-05:00[America/Bogota]","screenshots":[{"screenshot":"11a6b76b6e2717582bf1359db96f7be16e3986fa09601423ebb3507438751bd8.png","timeStamp":1677865875463}],"result":"SUCCESS","precondition":false,"level":2},{"number":15,"description":"Gestor present","duration":34,"startTime":"2023-03-03T12:51:15.464792300-05:00[America/Bogota]","screenshots":[{"screenshot":"11a6b76b6e2717582bf1359db96f7be16e3986fa09601423ebb3507438751bd8.png","timeStamp":1677865875499}],"result":"SUCCESS","precondition":false,"level":2},{"number":16,"description":"Gestor clicks on BOTTON SIGN IN","duration":339,"startTime":"2023-03-03T12:51:15.499389100-05:00[America/Bogota]","screenshots":[{"screenshot":"d793f36a1780f1872544fbd9bb1f951b007c8a632fd021db0247f4194809b357.png","timeStamp":1677865875838}],"result":"SUCCESS","precondition":false,"level":2},{"number":17,"description":"Gestor wait","duration":180241,"startTime":"2023-03-03T12:51:15.840936800-05:00[America/Bogota]","screenshots":[{"screenshot":"0c8d836bdd1235ab7245d04a180fb29b04ee2448d8d4be5f351442464feadba6.png","timeStamp":1677866056082}],"result":"SUCCESS","precondition":false,"level":2},{"number":18,"description":"Gestor clicks on BOTON PARA MANTENER INICIADA LA SESION","duration":15438,"startTime":"2023-03-03T12:54:16.083744500-05:00[America/Bogota]","screenshots":[{"screenshot":"e493cff7e07f5e064cd7af87b841c001e43e24b0117ccd8bc72f7ad552b4528e.png","timeStamp":1677866071522}],"result":"SUCCESS","precondition":false,"level":2},{"number":19,"description":"Gestor wait","duration":5565,"startTime":"2023-03-03T12:54:31.523077700-05:00[America/Bogota]","screenshots":[{"screenshot":"fbb6356931cf9ad79f805506ff5f9cad1f8625658d09e413d3649544129bbcbc.png","timeStamp":1677866077088}],"result":"SUCCESS","precondition":false,"level":2}]}]},{"number":20,"description":"When el gestor/admin crea un nuevo rol de Gestor RolGestor P_07","duration":7825,"startTime":"2023-03-03T12:54:37.092279800-05:00[America/Bogota]","screenshots":[{"screenshot":"7355b29433d6a8e66c93c52995bb9c8aa0a6b442b18b76bcfe253eaae5ee28c9.png","timeStamp":1677866084917}],"result":"SUCCESS","precondition":false,"level":0,"children":[{"number":21,"description":"Gestor create gestor role","duration":7817,"startTime":"2023-03-03T12:54:37.098204-05:00[America/Bogota]","screenshots":[{"screenshot":"7355b29433d6a8e66c93c52995bb9c8aa0a6b442b18b76bcfe253eaae5ee28c9.png","timeStamp":1677866084915}],"result":"SUCCESS","precondition":false,"level":1,"children":[{"number":22,"description":"Gestor clickable","duration":578,"startTime":"2023-03-03T12:54:37.104283-05:00[America/Bogota]","screenshots":[{"screenshot":"fbb6356931cf9ad79f805506ff5f9cad1f8625658d09e413d3649544129bbcbc.png","timeStamp":1677866077682}],"result":"SUCCESS","precondition":false,"level":2},{"number":23,"description":"Gestor clicks on Ingreso al Menú de seguridad","duration":255,"startTime":"2023-03-03T12:54:37.683917700-05:00[America/Bogota]","screenshots":[{"screenshot":"4fd63ef3f6baeba712481a5d5294371b8f355c2167ad95cc2303e106f5d4ac5f.png","timeStamp":1677866077939}],"result":"SUCCESS","precondition":false,"level":2},{"number":24,"description":"Gestor clickable","duration":417,"startTime":"2023-03-03T12:54:37.940465400-05:00[America/Bogota]","screenshots":[{"screenshot":"b31eff8feaef65abb32e4826d583c873c7aba12930de7a0afc6cf9aa653b85ac.png","timeStamp":1677866078357}],"result":"SUCCESS","precondition":false,"level":2},{"number":25,"description":"Gestor clicks on Ingreso al Menú de Gestión de Roles","duration":260,"startTime":"2023-03-03T12:54:38.358576900-05:00[America/Bogota]","screenshots":[{"screenshot":"5ec3cd192ef708dc723e7ec8967c5953cb26fb6a61ed6048b80fccd164af1e2d.png","timeStamp":1677866078618}],"result":"SUCCESS","precondition":false,"level":2},{"number":26,"description":"Gestor clickable","duration":41,"startTime":"2023-03-03T12:54:38.620061900-05:00[America/Bogota]","screenshots":[{"screenshot":"5ec3cd192ef708dc723e7ec8967c5953cb26fb6a61ed6048b80fccd164af1e2d.png","timeStamp":1677866078661}],"result":"SUCCESS","precondition":false,"level":2},{"number":27,"description":"Gestor clicks on Botón para Agregar usuario","duration":270,"startTime":"2023-03-03T12:54:38.661457800-05:00[America/Bogota]","screenshots":[{"screenshot":"64ad905a3bdcaee6ab61fa631070aa0fc0f88a5b43f00102a11eebc33f8f7319.png","timeStamp":1677866078932}],"result":"SUCCESS","precondition":false,"level":2},{"number":28,"description":"Gestor clickable","duration":39,"startTime":"2023-03-03T12:54:38.933140100-05:00[America/Bogota]","screenshots":[{"screenshot":"64ad905a3bdcaee6ab61fa631070aa0fc0f88a5b43f00102a11eebc33f8f7319.png","timeStamp":1677866078972}],"result":"SUCCESS","precondition":false,"level":2},{"number":29,"description":"Gestor clicks on Botón para Agregar usuario","duration":243,"startTime":"2023-03-03T12:54:38.973584300-05:00[America/Bogota]","screenshots":[{"screenshot":"175aba0230efb40d2a7f22616891a252d872550a3da9fec1b5b2db67ad11b679.png","timeStamp":1677866079217}],"result":"SUCCESS","precondition":false,"level":2},{"number":30,"description":"Gestor enters \u0027RolGestor P_07\u0027 into Botón para Agregar usuario","duration":347,"startTime":"2023-03-03T12:54:39.217196200-05:00[America/Bogota]","screenshots":[{"screenshot":"e53d9cc705d6a464ec674df6e74d81111e45d5b9e57630d422b577e2243290cf.png","timeStamp":1677866079564}],"result":"SUCCESS","precondition":false,"level":2},{"number":31,"description":"Gestor clicks on Boton guardar Rol","duration":216,"startTime":"2023-03-03T12:54:39.565605300-05:00[America/Bogota]","screenshots":[{"screenshot":"bf30c2a5a8c654670296c17dfd96f9b18df953bd16a12b6240e0be9e0953251d.png","timeStamp":1677866079781}],"result":"SUCCESS","precondition":false,"level":2},{"number":32,"description":"Gestor wait","duration":5131,"startTime":"2023-03-03T12:54:39.781989700-05:00[America/Bogota]","screenshots":[{"screenshot":"7355b29433d6a8e66c93c52995bb9c8aa0a6b442b18b76bcfe253eaae5ee28c9.png","timeStamp":1677866084913}],"result":"SUCCESS","precondition":false,"level":2}]}]},{"number":33,"description":"Then se vera nuevo rol en pantalla","duration":200,"startTime":"2023-03-03T12:54:44.917758700-05:00[America/Bogota]","screenshots":[{"screenshot":"7355b29433d6a8e66c93c52995bb9c8aa0a6b442b18b76bcfe253eaae5ee28c9.png","timeStamp":1677866085118}],"result":"SUCCESS","precondition":false,"level":0,"children":[{"number":34,"description":"Then val creation role ok","duration":197,"startTime":"2023-03-03T12:54:44.918758100-05:00[America/Bogota]","screenshots":[{"screenshot":"7355b29433d6a8e66c93c52995bb9c8aa0a6b442b18b76bcfe253eaae5ee28c9.png","timeStamp":1677866085116}],"result":"SUCCESS","precondition":false,"level":1}]}],"userStory":{"id":"gestionar-roles-para-acceso-de-los-colaboradores","storyName":"Gestionar Roles para acceso de los colaboradores","path":"file:///C:/Users/2462952/Documents/ReposVarios/ec-beneficios-auto-test/src/test/resources/co/com/tcs/certificacion/features/benefits/menu_roles_and_audit/roles_management.feature","narrative":"  Yo como Gestor/Admin\n  quiero gestionar los perfiles de los colaboradores\n  para validar permisos y restricciones de cada rol","type":"feature"},"featureTag":{"name":"Menu roles and audit/Gestionar Roles para acceso de los colaboradores","type":"feature","displayName":"Menu roles and audit/Gestionar Roles para acceso de los colaboradores"},"title":"Creación Rol Gestor","backgroundTitle":"Inicio Sesión como Gestor Senior/Admin","backgroundDescription":"","startTime":"2023-03-03T12:50:23.699264500-05:00[America/Bogota]","duration":261420,"projectKey":"","sessionId":"81f754273fbfa15ce3e244282d891235","driver":"chrome:gestor","isManualTestingUpToDate":false,"manual":false,"testSource":"Cucumber","actors":[{"name":"Gestor","can":["browse the web"]}],"result":"SUCCESS"}