{"name":"Crear usuario con perfil Multi Rol (Admin/Gestor/Auxiliar/Basic)","id":"gestionar-perfiles-de-los-colaboradores;crear-usuario-con-perfil-multi-rol-(admin/gestor/auxiliar/basic)","testSteps":[{"number":1,"description":"Given que el Gestor Senior/Admin inicia sesion con usuario jcaraballo@summa-sci.com con clave S4p+*2022++**","duration":219579,"startTime":"2023-03-03T12:34:47.071511200-05:00[America/Bogota]","screenshots":[{"screenshot":"fbb6356931cf9ad79f805506ff5f9cad1f8625658d09e413d3649544129bbcbc.png","timeStamp":1677865106651}],"result":"SUCCESS","precondition":false,"level":0,"children":[{"number":2,"description":"Gestor home page","duration":9201,"startTime":"2023-03-03T12:34:47.073524200-05:00[America/Bogota]","screenshots":[{"screenshot":"2a7791ba15962f8c5aaf5c7dda8ec8e08a9c8b927ab7a70adb90a7d966fe0fb6.png","timeStamp":1677864896274}],"result":"SUCCESS","precondition":false,"level":1,"children":[{"number":3,"description":"Gestor opens the https://app-expcolaborador-frontend-qa.azurewebsites.net","duration":9198,"startTime":"2023-03-03T12:34:47.074524300-05:00[America/Bogota]","screenshots":[{"screenshot":"2a7791ba15962f8c5aaf5c7dda8ec8e08a9c8b927ab7a70adb90a7d966fe0fb6.png","timeStamp":1677864896272}],"result":"SUCCESS","precondition":false,"level":2}]},{"number":4,"description":"Gestor login dir act","duration":210372,"startTime":"2023-03-03T12:34:56.276797900-05:00[America/Bogota]","screenshots":[{"screenshot":"fbb6356931cf9ad79f805506ff5f9cad1f8625658d09e413d3649544129bbcbc.png","timeStamp":1677865106649}],"result":"SUCCESS","precondition":false,"level":1,"children":[{"number":5,"description":"Gestor clicks on Caja USER","duration":4127,"startTime":"2023-03-03T12:34:56.292632400-05:00[America/Bogota]","screenshots":[{"screenshot":"9834fd6587d03dd41c2965c9276fb5f2c2ed3950183359ff83d253793bf32d04.png","timeStamp":1677864900419}],"result":"SUCCESS","precondition":false,"level":2},{"number":6,"description":"Gestor present","duration":2141,"startTime":"2023-03-03T12:35:00.420740300-05:00[America/Bogota]","screenshots":[{"screenshot":"f523dd964f3e7ea5eabbdc70adc155f3ba20ecb520119c14747a9f579cf2fc66.png","timeStamp":1677864902562}],"result":"SUCCESS","precondition":false,"level":2},{"number":7,"description":"Gestor clicks on Caja USER","duration":356,"startTime":"2023-03-03T12:35:02.563666800-05:00[America/Bogota]","screenshots":[{"screenshot":"7b6c6fb56f5f5e55716bc7e04a0de3052c40e5c08876f3ec04aeaf0aaf6552e8.png","timeStamp":1677864902919}],"result":"SUCCESS","precondition":false,"level":2},{"number":8,"description":"Gestor enters \u0027jcaraballo@summa-sci.com\u0027 into Caja USER","duration":496,"startTime":"2023-03-03T12:35:02.921183-05:00[America/Bogota]","screenshots":[{"screenshot":"ec091b913a3ab7a97628b42ceebc5768fe578dfb2522bb5fae6794a6775c18cc.png","timeStamp":1677864903417}],"result":"SUCCESS","precondition":false,"level":2},{"number":9,"description":"Gestor clicks on BOTTN NEXT","duration":360,"startTime":"2023-03-03T12:35:03.418938100-05:00[America/Bogota]","screenshots":[{"screenshot":"63a8824d36e3acc6bf22550592f833c3c426151d154fbafa193b78c57bca4e23.png","timeStamp":1677864903779}],"result":"SUCCESS","precondition":false,"level":2},{"number":10,"description":"Gestor present","duration":3570,"startTime":"2023-03-03T12:35:03.780076-05:00[America/Bogota]","screenshots":[{"screenshot":"d94aa94c527ee40ac618e88fb00ff55b728d2411c036eed21c1e96ce24d06f89.png","timeStamp":1677864907350}],"result":"SUCCESS","precondition":false,"level":2},{"number":11,"description":"Gestor clicks on Caja PASS","duration":236,"startTime":"2023-03-03T12:35:07.351204400-05:00[America/Bogota]","screenshots":[{"screenshot":"7b2e71ae5616380dc54f71f719d90c4a0437e11d50e1c94bb71adda1b1180532.png","timeStamp":1677864907587}],"result":"SUCCESS","precondition":false,"level":2},{"number":12,"description":"Gestor enters \u0027S4p+*2022++**\u0027 into Caja PASS","duration":326,"startTime":"2023-03-03T12:35:07.588323900-05:00[America/Bogota]","screenshots":[{"screenshot":"2957c17f030af06a1e53d20f0d3eda1d785340064781bde5492b130beee44be6.png","timeStamp":1677864907914}],"result":"SUCCESS","precondition":false,"level":2},{"number":13,"description":"Gestor clicks on BOTTON SIGN IN","duration":2118,"startTime":"2023-03-03T12:35:07.916634100-05:00[America/Bogota]","screenshots":[{"screenshot":"92a32410fab41567d2a23af91f44b487e6bfc59de3cd22b14321d8721234e8fb.png","timeStamp":1677864910035}],"result":"SUCCESS","precondition":false,"level":2},{"number":14,"description":"Gestor wait","duration":5252,"startTime":"2023-03-03T12:35:10.036926900-05:00[America/Bogota]","screenshots":[{"screenshot":"11a6b76b6e2717582bf1359db96f7be16e3986fa09601423ebb3507438751bd8.png","timeStamp":1677864915289}],"result":"SUCCESS","precondition":false,"level":2},{"number":15,"description":"Gestor present","duration":46,"startTime":"2023-03-03T12:35:15.289571300-05:00[America/Bogota]","screenshots":[{"screenshot":"11a6b76b6e2717582bf1359db96f7be16e3986fa09601423ebb3507438751bd8.png","timeStamp":1677864915335}],"result":"SUCCESS","precondition":false,"level":2},{"number":16,"description":"Gestor clicks on BOTTON SIGN IN","duration":338,"startTime":"2023-03-03T12:35:15.335794600-05:00[America/Bogota]","screenshots":[{"screenshot":"d793f36a1780f1872544fbd9bb1f951b007c8a632fd021db0247f4194809b357.png","timeStamp":1677864915674}],"result":"SUCCESS","precondition":false,"level":2},{"number":17,"description":"Gestor wait","duration":180244,"startTime":"2023-03-03T12:35:15.675232100-05:00[America/Bogota]","screenshots":[{"screenshot":"0c8d836bdd1235ab7245d04a180fb29b04ee2448d8d4be5f351442464feadba6.png","timeStamp":1677865095920}],"result":"SUCCESS","precondition":false,"level":2},{"number":18,"description":"Gestor clicks on BOTON PARA MANTENER INICIADA LA SESION","duration":5155,"startTime":"2023-03-03T12:38:15.922124800-05:00[America/Bogota]","screenshots":[{"screenshot":"e493cff7e07f5e064cd7af87b841c001e43e24b0117ccd8bc72f7ad552b4528e.png","timeStamp":1677865101077}],"result":"SUCCESS","precondition":false,"level":2},{"number":19,"description":"Gestor wait","duration":5568,"startTime":"2023-03-03T12:38:21.078124500-05:00[America/Bogota]","screenshots":[{"screenshot":"fbb6356931cf9ad79f805506ff5f9cad1f8625658d09e413d3649544129bbcbc.png","timeStamp":1677865106646}],"result":"SUCCESS","precondition":false,"level":2}]}]},{"number":20,"description":"When el gestor/admin crea un nuevo usuario test.multirol_11@test.com con Multi Rol Gestor - Admin - Auxiliar","duration":10445,"startTime":"2023-03-03T12:38:26.651260200-05:00[America/Bogota]","screenshots":[{"screenshot":"125427b5dc6c8d3b03cabcf5eee5aa869495cea18c308eb62b0fbd7d0190bc62.png","timeStamp":1677865117096}],"result":"SUCCESS","precondition":false,"level":0,"children":[{"number":21,"description":"Gestor create multi role user","duration":10437,"startTime":"2023-03-03T12:38:26.656255600-05:00[America/Bogota]","screenshots":[{"screenshot":"125427b5dc6c8d3b03cabcf5eee5aa869495cea18c308eb62b0fbd7d0190bc62.png","timeStamp":1677865117094}],"result":"SUCCESS","precondition":false,"level":1,"children":[{"number":22,"description":"Gestor clickable","duration":550,"startTime":"2023-03-03T12:38:26.668568700-05:00[America/Bogota]","screenshots":[{"screenshot":"fbb6356931cf9ad79f805506ff5f9cad1f8625658d09e413d3649544129bbcbc.png","timeStamp":1677865107219}],"result":"SUCCESS","precondition":false,"level":2},{"number":23,"description":"Gestor clicks on Ingreso al Menú de seguridad","duration":283,"startTime":"2023-03-03T12:38:27.220405100-05:00[America/Bogota]","screenshots":[{"screenshot":"e036e8ed04d46c5357e8b3aaa85cd18813c0631db5d64e9ec92dc298c88c31a8.png","timeStamp":1677865107503}],"result":"SUCCESS","precondition":false,"level":2},{"number":24,"description":"Gestor clickable","duration":46,"startTime":"2023-03-03T12:38:27.505635800-05:00[America/Bogota]","screenshots":[{"screenshot":"e036e8ed04d46c5357e8b3aaa85cd18813c0631db5d64e9ec92dc298c88c31a8.png","timeStamp":1677865107551}],"result":"SUCCESS","precondition":false,"level":2},{"number":25,"description":"Gestor clicks on Botón menú Usuarios ","duration":302,"startTime":"2023-03-03T12:38:27.552738-05:00[America/Bogota]","screenshots":[{"screenshot":"d41179690fb423bba065774ad0e915e3f9bd0bdf8c90a264f93e4f3dcd990c4a.png","timeStamp":1677865107855}],"result":"SUCCESS","precondition":false,"level":2},{"number":26,"description":"Gestor clickable","duration":38,"startTime":"2023-03-03T12:38:27.857679-05:00[America/Bogota]","screenshots":[{"screenshot":"d41179690fb423bba065774ad0e915e3f9bd0bdf8c90a264f93e4f3dcd990c4a.png","timeStamp":1677865107895}],"result":"SUCCESS","precondition":false,"level":2},{"number":27,"description":"Gestor clicks on Agregar usuario","duration":294,"startTime":"2023-03-03T12:38:27.895838100-05:00[America/Bogota]","screenshots":[{"screenshot":"e9312aa4c12a16d2f4b418017676671e3994f869cdd1a4b62641728e33accb2e.png","timeStamp":1677865108190}],"result":"SUCCESS","precondition":false,"level":2},{"number":28,"description":"Gestor clickable","duration":41,"startTime":"2023-03-03T12:38:28.192522800-05:00[America/Bogota]","screenshots":[{"screenshot":"e9312aa4c12a16d2f4b418017676671e3994f869cdd1a4b62641728e33accb2e.png","timeStamp":1677865108234}],"result":"SUCCESS","precondition":false,"level":2},{"number":29,"description":"Gestor clicks on Caja texto para editar nuevo USUARIO","duration":214,"startTime":"2023-03-03T12:38:28.234883300-05:00[America/Bogota]","screenshots":[{"screenshot":"384fcd4ad226e92098ac2545b2e09e64514a73b1379db556d1234b14534f8eee.png","timeStamp":1677865108449}],"result":"SUCCESS","precondition":false,"level":2},{"number":30,"description":"Gestor enters \u0027test.multirol_11@test.com\u0027 into Caja texto para editar nuevo USUARIO","duration":374,"startTime":"2023-03-03T12:38:28.450731600-05:00[America/Bogota]","screenshots":[{"screenshot":"ee860cf818095629db99f1372e4495a9aad6f959f9acea5759ede13605d24efa.png","timeStamp":1677865108825}],"result":"SUCCESS","precondition":false,"level":2},{"number":31,"description":"Gestor clickable","duration":46,"startTime":"2023-03-03T12:38:28.827449900-05:00[America/Bogota]","screenshots":[{"screenshot":"ee860cf818095629db99f1372e4495a9aad6f959f9acea5759ede13605d24efa.png","timeStamp":1677865108873}],"result":"SUCCESS","precondition":false,"level":2},{"number":32,"description":"Gestor clicks on Filtro para consultar Roles","duration":300,"startTime":"2023-03-03T12:38:28.873724700-05:00[America/Bogota]","screenshots":[{"screenshot":"d744184c335cd5c021ec6f9886b0aed1e04ecaed8a37fe42b900ee6d450d2d4a.png","timeStamp":1677865109174}],"result":"SUCCESS","precondition":false,"level":2},{"number":33,"description":"Gestor enters \u0027Gestor\u0027 into Filtro para consultar Roles","duration":293,"startTime":"2023-03-03T12:38:29.175237200-05:00[America/Bogota]","screenshots":[{"screenshot":"afc6aad804d927a860b9237394fb78f8b0b236ace01129208d339e61d61436f8.png","timeStamp":1677865109468}],"result":"SUCCESS","precondition":false,"level":2},{"number":34,"description":"Gestor clickable","duration":39,"startTime":"2023-03-03T12:38:29.469578900-05:00[America/Bogota]","screenshots":[{"screenshot":"afc6aad804d927a860b9237394fb78f8b0b236ace01129208d339e61d61436f8.png","timeStamp":1677865109508}],"result":"SUCCESS","precondition":false,"level":2},{"number":35,"description":"Gestor clicks on CheckBox Admin Rol","duration":239,"startTime":"2023-03-03T12:38:29.509319800-05:00[America/Bogota]","screenshots":[{"screenshot":"861a6d15ddc540fa758efb6330536ab347e568501f98c811fcca98e066f8da91.png","timeStamp":1677865109748}],"result":"SUCCESS","precondition":false,"level":2},{"number":36,"description":"Gestor clickable","duration":207,"startTime":"2023-03-03T12:38:29.750129300-05:00[America/Bogota]","screenshots":[{"screenshot":"f6a7035f48341d42a6839cfdf4b81fa17fb6a3983e0df7e8f4c2617a012e2e36.png","timeStamp":1677865109957}],"result":"SUCCESS","precondition":false,"level":2},{"number":37,"description":"Gestor clicks on Filtro para consultar Roles","duration":265,"startTime":"2023-03-03T12:38:29.958964500-05:00[America/Bogota]","screenshots":[{"screenshot":"2cbcc468e105170e32d5926402e921caa94a8e0a96de2a7f6a05593e479e7b0a.png","timeStamp":1677865110224}],"result":"SUCCESS","precondition":false,"level":2},{"number":38,"description":"Gestor enters \u0027Admin\u0027 into Filtro para consultar Roles","duration":292,"startTime":"2023-03-03T12:38:30.226485500-05:00[America/Bogota]","screenshots":[{"screenshot":"a46c0ac1605dd3183280777e3b7837face0b964c49255b351b8feb72cac81ef0.png","timeStamp":1677865110519}],"result":"SUCCESS","precondition":false,"level":2},{"number":39,"description":"Gestor clickable","duration":44,"startTime":"2023-03-03T12:38:30.520957-05:00[America/Bogota]","screenshots":[{"screenshot":"a46c0ac1605dd3183280777e3b7837face0b964c49255b351b8feb72cac81ef0.png","timeStamp":1677865110565}],"result":"SUCCESS","precondition":false,"level":2},{"number":40,"description":"Gestor clicks on CheckBox Admin Rol","duration":240,"startTime":"2023-03-03T12:38:30.566591600-05:00[America/Bogota]","screenshots":[{"screenshot":"b93f73e326679c1ffdd28ca7966bc01360c6d73ccab3a81bcbe404691e5fc635.png","timeStamp":1677865110806}],"result":"SUCCESS","precondition":false,"level":2},{"number":41,"description":"Gestor clickable","duration":45,"startTime":"2023-03-03T12:38:30.808722100-05:00[America/Bogota]","screenshots":[{"screenshot":"b93f73e326679c1ffdd28ca7966bc01360c6d73ccab3a81bcbe404691e5fc635.png","timeStamp":1677865110853}],"result":"SUCCESS","precondition":false,"level":2},{"number":42,"description":"Gestor clicks on Filtro para consultar Roles","duration":231,"startTime":"2023-03-03T12:38:30.853904300-05:00[America/Bogota]","screenshots":[{"screenshot":"abbf3ef185e1b2d14b6f9a3e833ae13b92258cdda7f7c380e7d6ce5a4edc42dd.png","timeStamp":1677865111085}],"result":"SUCCESS","precondition":false,"level":2},{"number":43,"description":"Gestor enters \u0027Auxiliar\u0027 into Filtro para consultar Roles","duration":287,"startTime":"2023-03-03T12:38:31.086050100-05:00[America/Bogota]","screenshots":[{"screenshot":"f001662d9e4e2f68579dcc7dc8d45a7e910cc83c85093380278d8c0a1811588e.png","timeStamp":1677865111372}],"result":"SUCCESS","precondition":false,"level":2},{"number":44,"description":"Gestor clickable","duration":40,"startTime":"2023-03-03T12:38:31.373441800-05:00[America/Bogota]","screenshots":[{"screenshot":"f001662d9e4e2f68579dcc7dc8d45a7e910cc83c85093380278d8c0a1811588e.png","timeStamp":1677865111413}],"result":"SUCCESS","precondition":false,"level":2},{"number":45,"description":"Gestor clicks on CheckBox Admin Rol","duration":257,"startTime":"2023-03-03T12:38:31.413838700-05:00[America/Bogota]","screenshots":[{"screenshot":"05fe7f2be7adc7cbd20c90aece46bc6081da3c64016343ab52d89df7e5a19428.png","timeStamp":1677865111671}],"result":"SUCCESS","precondition":false,"level":2},{"number":46,"description":"Gestor clicks on Boton guardar usuario","duration":247,"startTime":"2023-03-03T12:38:31.672730200-05:00[America/Bogota]","screenshots":[{"screenshot":"a26c9aebfacda6a4e5ff79beaf3f4be2685a0417dd02963cc40243f2c0a97fcb.png","timeStamp":1677865111919}],"result":"SUCCESS","precondition":false,"level":2},{"number":47,"description":"Gestor wait","duration":5171,"startTime":"2023-03-03T12:38:31.921531500-05:00[America/Bogota]","screenshots":[{"screenshot":"125427b5dc6c8d3b03cabcf5eee5aa869495cea18c308eb62b0fbd7d0190bc62.png","timeStamp":1677865117092}],"result":"SUCCESS","precondition":false,"level":2}]}]},{"number":48,"description":"Then se podra ver nuevo usuario en la pantalla","duration":201,"startTime":"2023-03-03T12:38:37.097227200-05:00[America/Bogota]","screenshots":[{"screenshot":"8c5634cbf610f850dc3d0572793ff16fe31c1b8261dee3459d414b58ba1f4554.png","timeStamp":1677865117298}],"result":"SUCCESS","precondition":false,"level":0,"children":[{"number":49,"description":"Then val creation user ok","duration":197,"startTime":"2023-03-03T12:38:37.098321700-05:00[America/Bogota]","screenshots":[{"screenshot":"8c5634cbf610f850dc3d0572793ff16fe31c1b8261dee3459d414b58ba1f4554.png","timeStamp":1677865117295}],"result":"SUCCESS","precondition":false,"level":1}]}],"userStory":{"id":"gestionar-perfiles-de-los-colaboradores","storyName":"Gestionar perfiles de los colaboradores","path":"file:///C:/Users/2462952/Documents/ReposVarios/ec-beneficios-auto-test/src/test/resources/co/com/tcs/certificacion/features/benefits/menu_roles_and_audit/user_management.feature","narrative":"  Yo como Usuario\n  quiero gestionar los perfiles de los colaboradores\n  para validar permisos y restricciones de cada perfil","type":"feature"},"featureTag":{"name":"Menu roles and audit/Gestionar perfiles de los colaboradores","type":"feature","displayName":"Menu roles and audit/Gestionar perfiles de los colaboradores"},"title":"Crear usuario con perfil Multi Rol (Admin/Gestor/Auxiliar/Basic)","backgroundTitle":"Inicio Sesión como Gestor Senior/Admin","backgroundDescription":"","startTime":"2023-03-03T12:34:47.068530700-05:00[America/Bogota]","duration":230230,"projectKey":"","sessionId":"d442fa25d0722e467dbc5f6d66e1972c","driver":"chrome:gestor","isManualTestingUpToDate":false,"manual":false,"testSource":"Cucumber","actors":[{"name":"Gestor","can":["browse the web"]}],"result":"SUCCESS"}